chessli/__init__.py
chessli/cli/__init__.py
chessli/cli/games.py
chessli/cli/main.py
chessli/cli/openings.py
chessli/cli/option_callbacks.py
chessli/cli/stats.py
chessli/cli/tactics.py
chessli/enums.py
chessli/games.py
chessli/mistakes.py
chessli/openings.py
chessli/rich_logging.py
chessli/tactics.py
chessli/utils.py
chessli-0.2.4.dist-info/entry_points.txt
chessli-0.2.4.dist-info/LICENSE
chessli-0.2.4.dist-info/WHEEL
chessli-0.2.4.dist-info/METADATA
chessli-0.2.4.dist-info/RECORD
