Metadata-Version: 2.1
Name: chessli
Version: 0.2.4
Summary: A free and open source chess improvement app that combines the power of lichess and anki
Home-page: https://github.com/pwenker/chessli
License: MIT
Author: Pascal Wenker
Author-email: pwenker@posteo.de
Requires-Python: >=3.7.1,<4.0.0
Classifier: Environment :: Console
Classifier: Intended Audience :: Developers
Classifier: Intended Audience :: End Users/Desktop
Classifier: License :: OSI Approved :: MIT License
Classifier: Operating System :: MacOS
Classifier: Operating System :: Microsoft :: Windows
Classifier: Operating System :: POSIX :: Linux
Classifier: Programming Language :: Python :: 3
Classifier: Programming Language :: Python :: 3.6
Classifier: Programming Language :: Python :: 3.7
Classifier: Programming Language :: Python :: 3.8
Classifier: Programming Language :: Python :: 3.9
Classifier: Topic :: Games/Entertainment
Classifier: Typing :: Typed
Requires-Dist: appdirs (>=1.4.4,<2.0.0)
Requires-Dist: berserk (>=0.10.0,<0.11.0)
Requires-Dist: matplotlib (>=3.3.3,<4.0.0)
Requires-Dist: omegaconf (>=2.0.6,<3.0.0)
Requires-Dist: pandas (>=1.2.0,<2.0.0)
Requires-Dist: python-chess (>=1.999,<2.0)
Requires-Dist: rich (>=9.9.0,<10.0.0)
Requires-Dist: seaborn (>=0.11.1,<0.12.0)
Requires-Dist: typer (>=0.3.2,<0.4.0)
Project-URL: Documentation, https://pwenker.github.io/chessli
